redial22/__init__.py
redial22/__main__.py
redial22/config.py
redial22/hostinfo.py
redial22/redial.py
redial22/uistate.py
redial22/utils.py
redial22/xdg.py
redial22/tree/__init__.py
redial22/tree/node.py
redial22/ui/__init__.py
redial22/ui/dialog.py
redial22/ui/footer.py
redial22/ui/palette.py
redial22/ui/tree.py
redial22-1.2.1.dist-info/licenses/LICENSE
redial22-1.2.1.dist-info/METADATA
redial22-1.2.1.dist-info/WHEEL
redial22-1.2.1.dist-info/entry_points.txt
redial22-1.2.1.dist-info/top_level.txt
redial22-1.2.1.dist-info/RECORD
