Metadata-Version: 2.4
Name: redial22
Version: 1.2.1
Summary: SSH Connection Manager Improved
Home-page: https://github.com/FelipeMiranda/redial22
Author: Felipe Miranda
Author-email: felipemiranda@outlook.com
License: gpl3
Platform: any
Classifier: Development Status :: 4 - Beta
Classifier: Programming Language :: Python :: 3
Classifier: Environment :: Console
Classifier: Operating System :: POSIX :: Linux
Classifier: Operating System :: MacOS :: MacOS X
License-File: LICENSE
Requires-Dist: urwid==2.1.2
Provides-Extra: testing
Requires-Dist: pytest; extra == "testing"
Requires-Dist: pytest-cov; extra == "testing"
Dynamic: description-content-type
Dynamic: license-file
